snakehouse/__init__.py
snakehouse/bootstrap.py
snakehouse/build.py
snakehouse/faster_builds.py
snakehouse/multibuild.py
snakehouse/requirements.py
snakehouse/satella.py
snakehouse/templating.py
snakehouse-2.3.dist-info/LICENSE
snakehouse-2.3.dist-info/METADATA
snakehouse-2.3.dist-info/WHEEL
snakehouse-2.3.dist-info/top_level.txt
snakehouse-2.3.dist-info/RECORD
