Metadata-Version: 2.1
Name: snakehouse
Version: 2.3
Summary: Utilities for packing multiple pyx files into a single Cython extension
Home-page: https://git.dms-serwis.com.pl/smokserwis/snakehouse
Author: Piotr Maślanka
Author-email: pmaslanka@smok.co
Project-URL: Code, https://git.dms-serwis.com.pl/smokserwis/snakehouse
Project-URL: Issue tracker, https://git.dms-serwis.com.pl/smokserwis/snakehouse/-/issues
Keywords: cython,extension,multiple,pyx
Classifier: Programming Language :: Python
Classifier: Programming Language :: Python :: 3.5
Classifier: Programming Language :: Python :: 3.6
Classifier: Programming Language :: Python :: 3.7
Classifier: Programming Language :: Python :: 3.8
Classifier: Programming Language :: Python :: 3.9
Classifier: Programming Language :: Python :: 3.10
Classifier: Programming Language :: Python :: 3.11
Classifier: Programming Language :: Python :: Implementation :: CPython
Classifier: Operating System :: OS Independent
Classifier: Development Status :: 5 - Production/Stable
Classifier: License :: OSI Approved :: MIT License
Classifier: Topic :: Software Development :: Code Generators
Classifier: Topic :: Software Development :: Build Tools
Requires-Python: !=2.7.*,!=3.0.*,!=3.1.*,!=3.2.*,!=3.3.*,!=3.4.*
License-File: LICENSE
Requires-Dist: Cython
